memorix_client_redis/__init__.py
memorix_client_redis/cache/__init__.py
memorix_client_redis/cache/cache_base.py
memorix_client_redis/cache/cache_item.py
memorix_client_redis/cache/cache_options.py
memorix_client_redis/example-schema.memorix
memorix_client_redis/example_schema_generated.py
memorix_client_redis/hash_key.py
memorix_client_redis/json.py
memorix_client_redis/memorix_base.py
memorix_client_redis/pubsub/__init__.py
memorix_client_redis/pubsub/pubsub_base.py
memorix_client_redis/pubsub/pubsub_item.py
memorix_client_redis/py.typed
memorix_client_redis/redis_connection.py
memorix_client_redis/start.py
memorix_client_redis/task/__init__.py
memorix_client_redis/task/task_base.py
memorix_client_redis/task/task_item.py
memorix_client_redis/task/task_options.py
memorix_client_redis/value.py
memorix_client_redis-2.1.4.dist-info/METADATA
memorix_client_redis-2.1.4.dist-info/WHEEL
memorix_client_redis-2.1.4.dist-info/entry_points.txt
memorix_client_redis-2.1.4.dist-info/RECORD
