Metadata-Version: 2.1
Name: memorix_client_redis
Version: 2.1.4
Summary: 
Author: Yuval Saraf
Author-email: unimonkiez@gmail.com
Requires-Python: >=3.10,<4.0
Classifier: Programming Language :: Python :: 3
Classifier: Programming Language :: Python :: 3.10
Classifier: Programming Language :: Python :: 3.11
Classifier: Programming Language :: Python :: 3.12
Requires-Dist: dacite (>=1.6.0,<2.0.0)
Requires-Dist: redis (>=4.3.4,<5.0.0)
Requires-Dist: typing-extensions (>=4.4.0,<5.0.0)
